czl/__init__.py
czl/_base_client.py
czl/_client.py
czl/_compat.py
czl/_constants.py
czl/_exceptions.py
czl/_files.py
czl/_models.py
czl/_qs.py
czl/_resource.py
czl/_response.py
czl/_streaming.py
czl/_types.py
czl/_version.py
czl/py.typed
czl/_utils/__init__.py
czl/_utils/_logs.py
czl/_utils/_proxy.py
czl/_utils/_reflection.py
czl/_utils/_streams.py
czl/_utils/_sync.py
czl/_utils/_transform.py
czl/_utils/_typing.py
czl/_utils/_utils.py
czl/lib/.keep
czl/resources/__init__.py
czl/resources/pets.py
czl/resources/user.py
czl/resources/store/__init__.py
czl/resources/store/order.py
czl/resources/store/store.py
czl/types/__init__.py
czl/types/api_response.py
czl/types/pet.py
czl/types/pet_create_params.py
czl/types/pet_find_by_status_params.py
czl/types/pet_find_by_status_response.py
czl/types/pet_find_by_tags_params.py
czl/types/pet_find_by_tags_response.py
czl/types/pet_update_by_id_params.py
czl/types/pet_update_params.py
czl/types/pet_upload_image_params.py
czl/types/store_create_order_params.py
czl/types/store_inventory_response.py
czl/types/user.py
czl/types/user_create_params.py
czl/types/user_create_with_list_params.py
czl/types/user_login_params.py
czl/types/user_login_response.py
czl/types/user_param.py
czl/types/user_update_params.py
czl/types/shared/__init__.py
czl/types/shared/order.py
czl/types/store/__init__.py
czl-0.1.0a1.dist-info/METADATA
czl-0.1.0a1.dist-info/WHEEL
czl-0.1.0a1.dist-info/licenses/LICENSE
czl-0.1.0a1.dist-info/RECORD
